<annotation>
  <folder>VOC2014_instance/eating</folder>
  <filename>download (1).jpg</filename>
  <source>
    <database>MS COCO 2014</database>
    <annotation>MS COCO 2014</annotation>
    <image>Flickr</image>
  </source>
  <size>
    <width>265</width>
    <height>190</height>
    <depth>3</depth>
  </size>
  <segmented>0</segmented>
  <object>
    <name>eating</name>
    <bndbox>
      <xmin>93.0</xmin>
      <ymin>19.0</ymin>
      <xmax>167.0</xmax>
      <ymax>142.0</ymax>
    </bndbox>
    <difficult>0</difficult>
  </object>
</annotation>
